admobilizeapis-2025.10.24.post1-py3.6-nspkg.pth
admobilize/google/__init__.py
admobilize/google/longrunning/__init__.py
admobilize/google/longrunning/operations_pb2.py
admobilize/google/longrunning/operations_pb2_grpc.py
admobilize/proto/__init__.py
admobilize/proto/admprovider/__init__.py
admobilize/proto/admprovider/v1alpha1/__init__.py
admobilize/proto/admprovider/v1alpha1/admprovider_service_pb2.py
admobilize/proto/admprovider/v1alpha1/admprovider_service_pb2_grpc.py
admobilize/proto/admprovider/v1alpha1/resources_pb2.py
admobilize/proto/admprovider/v1alpha1/resources_pb2_grpc.py
admobilize/proto/ayuda/__init__.py
admobilize/proto/ayuda/v1alpha1/__init__.py
admobilize/proto/ayuda/v1alpha1/ayuda_service_pb2.py
admobilize/proto/ayuda/v1alpha1/ayuda_service_pb2_grpc.py
admobilize/proto/ayuda/v1alpha1/resources_pb2.py
admobilize/proto/ayuda/v1alpha1/resources_pb2_grpc.py
admobilize/proto/billing/__init__.py
admobilize/proto/billing/v1alpha1/__init__.py
admobilize/proto/billing/v1alpha1/billing_pb2.py
admobilize/proto/billing/v1alpha1/billing_pb2_grpc.py
admobilize/proto/brightauthor/__init__.py
admobilize/proto/brightauthor/v1alpha1/__init__.py
admobilize/proto/brightauthor/v1alpha1/brightauthor_service_pb2.py
admobilize/proto/brightauthor/v1alpha1/brightauthor_service_pb2_grpc.py
admobilize/proto/brightauthor/v1alpha1/resources_pb2.py
admobilize/proto/brightauthor/v1alpha1/resources_pb2_grpc.py
admobilize/proto/broadsign/__init__.py
admobilize/proto/broadsign/v1alpha1/__init__.py
admobilize/proto/broadsign/v1alpha1/broadsign_service_pb2.py
admobilize/proto/broadsign/v1alpha1/broadsign_service_pb2_grpc.py
admobilize/proto/broadsign/v1alpha1/resources_pb2.py
admobilize/proto/broadsign/v1alpha1/resources_pb2_grpc.py
admobilize/proto/cmsintegrations/__init__.py
admobilize/proto/cmsintegrations/v1/__init__.py
admobilize/proto/cmsintegrations/v1/cmsintegrations_service_pb2.py
admobilize/proto/cmsintegrations/v1/cmsintegrations_service_pb2_grpc.py
admobilizeapis-2025.10.24.post1.dist-info/METADATA
admobilizeapis-2025.10.24.post1.dist-info/WHEEL
admobilizeapis-2025.10.24.post1.dist-info/namespace_packages.txt
admobilizeapis-2025.10.24.post1.dist-info/top_level.txt
admobilizeapis-2025.10.24.post1.dist-info/RECORD
