Metadata-Version: 2.1
Name: admobilizeapis
Version: 2025.10.24.post1
Summary: Protobufs used in AdMobilize Ecosystem
Home-page: https://www.bitbucket.org/admobilize/admobilizeapis
Author: AdMobilize Team
Author-email: devel@admobilize.com
License: GPLv3
Platform: UNKNOWN
Classifier: Development Status :: 4 - Beta
Classifier: Intended Audience :: Developers
Classifier: License :: OSI Approved :: GNU General Public License v3 (GPLv3)
Classifier: Programming Language :: Python
Classifier: Programming Language :: Python :: 2
Classifier: Programming Language :: Python :: 2.7
Classifier: Programming Language :: Python :: 3
Classifier: Programming Language :: Python :: 3.4
Classifier: Programming Language :: Python :: 3.5
Classifier: Programming Language :: Python :: 3.6
Requires-Dist: google-api-core (<2.0.0dev,>=1.6.0)
Requires-Dist: protobuf (<4.0,>=3.6.0)
Provides-Extra: grpc
Requires-Dist: grpcio (>=1.2.0) ; extra == 'grpc'
